xcash/__init__.py
xcash/__main__.py
xcash/blockchainExplorer.py
xcash/delegatesExplorer.py
xcash/helpers.py
xcash/sharedDelegate.py
xcash-0.1.0.dist-info/LICENSE
xcash-0.1.0.dist-info/METADATA
xcash-0.1.0.dist-info/WHEEL
xcash-0.1.0.dist-info/top_level.txt
xcash-0.1.0.dist-info/RECORD
