Metadata-Version: 2.1
Name: xcash
Version: 0.1.0
Summary: XCASH Foundation ecosystem API wrapper
Home-page: https://github.com/X-CASH-official/XCASH-Ecosystem-api-wrapper
Author: AnimusXCASH
Author-email: lovro@xcash.foundation
License: MIT
Platform: UNKNOWN
Classifier: License :: OSI Approved :: MIT License
Classifier: Programming Language :: Python :: 3
Classifier: Programming Language :: Python :: 3.9
License-File: LICENSE
Requires-Dist: requests
